ajlpypubtest/__init__.py
ajlpypubtest/_version.py
ajlpypubtest/build_helper.py
ajlpypubtest/example.py
ajlpypubtest-0.2.0.dist-info/licenses/LICENSE
ajlpypubtest-0.2.0.dist-info/METADATA
ajlpypubtest-0.2.0.dist-info/WHEEL
ajlpypubtest-0.2.0.dist-info/top_level.txt
ajlpypubtest-0.2.0.dist-info/RECORD
