Metadata-Version: 2.4
Name: ajlpypubtest
Version: 0.2.0
Summary: AJl python publishing tester
Author-email: Andy Loftus <aloftus@gmail.com>
Project-URL: Repository, https://github.com/andylytical/ajlpypubtest
Classifier: Programming Language :: Python :: 3
Requires-Python: >=3.6
License-File: LICENSE
Dynamic: license-file
